sphinx_nameko_theme/__init__.py
sphinx_nameko_theme/nameko/layout.html
sphinx_nameko_theme/nameko/reference.html
sphinx_nameko_theme/nameko/relations.html
sphinx_nameko_theme/nameko/theme.conf
sphinx_nameko_theme/nameko/static/nameko.css_t
sphinx_nameko_theme/nameko/static/pygments.css
sphinx_nameko_theme_cn-0.0.3.dist-info/LICENSE
sphinx_nameko_theme_cn-0.0.3.dist-info/METADATA
sphinx_nameko_theme_cn-0.0.3.dist-info/WHEEL
sphinx_nameko_theme_cn-0.0.3.dist-info/entry_points.txt
sphinx_nameko_theme_cn-0.0.3.dist-info/top_level.txt
sphinx_nameko_theme_cn-0.0.3.dist-info/RECORD
