Metadata-Version: 2.1
Name: sphinx-nameko-theme-cn
Version: 0.0.3
Summary: Sphinx Nameko Theme Chinese
Home-page: https://github.com/huyidao625/sphinx-nameko-theme
Author: hufei
Author-email: hufei625@qq.com
License: MIT
Platform: UNKNOWN
Classifier: Intended Audience :: Developers
Classifier: License :: OSI Approved :: MIT License
Classifier: Natural Language :: English
Classifier: Operating System :: OS Independent
Classifier: Programming Language :: Python
Classifier: Topic :: Internet
Classifier: Topic :: Software Development :: Documentation
Requires-Dist: sphinx
